LICENSE.txt
MANIFEST.in
README.rst
setup.py
datetimewidget/__init__.py
datetimewidget/widgets.py
datetimewidget/locale/en/LC_MESSAGES/django.mo
datetimewidget/locale/en/LC_MESSAGES/django.po
datetimewidget/locale/eu/LC_MESSAGES/django.mo
datetimewidget/locale/eu/LC_MESSAGES/django.po
datetimewidget/locale/it/LC_MESSAGES/django.mo
datetimewidget/locale/it/LC_MESSAGES/django.po
datetimewidget/static/css/datetimepicker.css
datetimewidget/static/js/bootstrap-datetimepicker.js
datetimewidget/static/js/moment.js
datetimewidget/static/js/locales/bootstrap-datetimepicker.ar.js
datetimewidget/static/js/locales/bootstrap-datetimepicker.bg.js
datetimewidget/static/js/locales/bootstrap-datetimepicker.ca.js
datetimewidget/static/js/locales/bootstrap-datetimepicker.cs.js
datetimewidget/static/js/locales/bootstrap-datetimepicker.da.js
datetimewidget/static/js/locales/bootstrap-datetimepicker.de.js
datetimewidget/static/js/locales/bootstrap-datetimepicker.ee.js
datetimewidget/static/js/locales/bootstrap-datetimepicker.el.js
datetimewidget/static/js/locales/bootstrap-datetimepicker.es.js
datetimewidget/static/js/locales/bootstrap-datetimepicker.eu.js
datetimewidget/static/js/locales/bootstrap-datetimepicker.fi.js
datetimewidget/static/js/locales/bootstrap-datetimepicker.fr.js
datetimewidget/static/js/locales/bootstrap-datetimepicker.he.js
datetimewidget/static/js/locales/bootstrap-datetimepicker.hr.js
datetimewidget/static/js/locales/bootstrap-datetimepicker.hu.js
datetimewidget/static/js/locales/bootstrap-datetimepicker.id.js
datetimewidget/static/js/locales/bootstrap-datetimepicker.is.js
datetimewidget/static/js/locales/bootstrap-datetimepicker.it.js
datetimewidget/static/js/locales/bootstrap-datetimepicker.ja.js
datetimewidget/static/js/locales/bootstrap-datetimepicker.ko.js
datetimewidget/static/js/locales/bootstrap-datetimepicker.kr.js
datetimewidget/static/js/locales/bootstrap-datetimepicker.lt.js
datetimewidget/static/js/locales/bootstrap-datetimepicker.lv.js
django_datetime_widget_fa.egg-info/PKG-INFO
django_datetime_widget_fa.egg-info/SOURCES.txt
django_datetime_widget_fa.egg-info/dependency_links.txt
django_datetime_widget_fa.egg-info/not-zip-safe
django_datetime_widget_fa.egg-info/requires.txt
django_datetime_widget_fa.egg-info/top_level.txt