Metadata-Version: 1.1
Name: django-datetime-widget-fa
Version: 0.9.6
Summary: Django-datetime-widget is a simple and clean widget for DateField, Timefiled and DateTimeField  in Django framework. It is based on Bootstrap datetime picker, supports both Bootstrap 3 and Bootstrap 2, and supports Font-Awesome. Special thanks to Alfredo Saglimbeni [https://github.com/asaglimbeni] for django-datetime-widget
Home-page: UNKNOWN
Author: Kamo Petrosyan
Author-email: kamo@haikson.com
License: BSD
Platform: UNKNOWN
Classifier: Development Status :: 4 - Beta
Classifier: Environment :: Web Environment
Classifier: Framework :: Django
Classifier: Intended Audience :: Developers
Classifier: Operating System :: OS Independent
Classifier: Programming Language :: Python
Classifier: License :: OSI Approved :: BSD License
Classifier: Topic :: Software Development :: Libraries :: Python Modules 
